brainmaze_torch/__init__.py
brainmaze_torch/_config.py
brainmaze_torch/_version.py
brainmaze_torch/models_generic.py
brainmaze_torch/seizure_detection/__init__.py
brainmaze_torch/seizure_detection/_seizure_detect.py
brainmaze_torch/seizure_detection/_models/__init__.py
brainmaze_torch/seizure_detection/_models/modelA_paper.pt
brainmaze_torch/seizure_detection/_models/modelB_full.pt
brainmaze_torch-0.1.1.dist-info/licenses/LICENSE
docs_src/source/conf.py
brainmaze_torch-0.1.1.dist-info/METADATA
brainmaze_torch-0.1.1.dist-info/WHEEL
brainmaze_torch-0.1.1.dist-info/top_level.txt
brainmaze_torch-0.1.1.dist-info/RECORD
