Metadata-Version: 2.4
Name: brainmaze-torch
Version: 0.1.1
Summary: BrainMaze: Brain Electrophysiology, Behavior and Dynamics Analysis Toolbox - Torch
Home-page: https://github.com/bnelair/brainmaze_torch
Author: Filip Mivalt
Author-email: Filip Mivalt <mivalt.filip@mayo.edu>
License: BSD-3-Clause
Project-URL: Homepage, https://github.com/bnelair/brainmaze_torch
Classifier: Topic :: Scientific/Engineering :: Medical Science Apps.
Classifier: Development Status :: 3 - Alpha
Classifier: Programming Language :: Python
Classifier: Programming Language :: Python :: 3
Classifier: Programming Language :: Python :: 3.9
Classifier: Programming Language :: Python :: 3.10
Classifier: Programming Language :: Python :: 3.11
Classifier: Programming Language :: Python :: 3.12
Classifier: Operating System :: OS Independent
Classifier: License :: OSI Approved :: BSD License
Classifier: Intended Audience :: Healthcare Industry
Classifier: Intended Audience :: Science/Research
Requires-Python: >=3.9.0
License-File: LICENSE
Requires-Dist: setuptools
Requires-Dist: sphinx
Requires-Dist: sphinx_book_theme
Requires-Dist: brainmaze_utils
Requires-Dist: pandas
Requires-Dist: pytz
Requires-Dist: python-dateutil
Requires-Dist: scikit-learn
Requires-Dist: tqdm
Requires-Dist: matplotlib
Requires-Dist: pyyaml
Requires-Dist: torch
Requires-Dist: torchvision
Requires-Dist: torchaudio
Provides-Extra: test
Requires-Dist: pytest~=8.4.2; extra == "test"
Requires-Dist: pytest-order; extra == "test"
Dynamic: author
Dynamic: home-page
Dynamic: license-file
Dynamic: requires-python
